zero/__init__.py
zero/cli.py
zero/logger.py
myzero-0.0.0.dist-info/METADATA
myzero-0.0.0.dist-info/WHEEL
myzero-0.0.0.dist-info/entry_points.txt
myzero-0.0.0.dist-info/top_level.txt
myzero-0.0.0.dist-info/RECORD
